cubehandler/__init__.py
cubehandler/cube.py
cubehandler/version.py
cubehandler/cli/__init__.py
cubehandler/cli/main.py
cubehandler/cli/commands/__init__.py
cubehandler/cli/commands/shrink.py
cubehandler-0.1.0.dist-info/entry_points.txt
cubehandler-0.1.0.dist-info/WHEEL
cubehandler-0.1.0.dist-info/METADATA
cubehandler-0.1.0.dist-info/RECORD
